ganondorf/__init__.py
ganondorf/__main__.py
ganondorf/core/CMakeLists.txt
ganondorf/core/datacore.cp39-win_amd64.pyd
ganondorf/core/include/ganondorf/arrayfunctions.h
ganondorf/core/include/ganondorf/datacore.h
ganondorf/core/include/ganondorf/datasettype.h
ganondorf/core/src/data/CMakeLists.txt
ganondorf/core/src/data/arrayfunctions.c
ganondorf/core/src/data/datacore.c
ganondorf/core/src/data/datasettype.c
ganondorf/cyclegan/__init__.py
ganondorf/data/__init__.py
ganondorf/data/dataset.py
ganondorf/data/dataset_loader.py
ganondorf/data/format_image_data.py
ganondorf/data/format_raw_data.py
ganondorf/data/image_dataset.py
ganondorf/data/text_dataset.py
ganondorf/data/visualizer.py
ganondorf/data/datasets/__init__.py
ganondorf/layers/__init__.py
ganondorf/layers/blocks.py
ganondorf/layers/residual.py
ganondorf/pix2pix/__init__.py
ganondorf/pix2pix/discriminator.py
ganondorf/pix2pix/generator.py
ganondorf/pix2pix/run.py
ganondorf/segmentation/__init__.py
ganondorf/segmentation/__main__.py
ganondorf/segmentation/segment.py
ganondorf/transfer/__init__.py
ganondorf/transfer/__main__.py
ganondorf/transfer/segment_transfer.py
ganondorf/transfer/transfer.py
ganondorf/transfer/transfer_classif_old.py
tests/data/__init__.py
tests/data/test_format_raw_data.py
tests/data/data/__init__.py
ganondorf-0.0.4.dist-info/LICENSE
ganondorf-0.0.4.dist-info/METADATA
ganondorf-0.0.4.dist-info/WHEEL
ganondorf-0.0.4.dist-info/top_level.txt
ganondorf-0.0.4.dist-info/zip-safe
ganondorf-0.0.4.dist-info/RECORD
